treys/__init__.py
treys/card.py
treys/deck.py
treys/evaluator.py
treys/lookup.py
treys-0.1.7.dist-info/LICENSE
treys-0.1.7.dist-info/METADATA
treys-0.1.7.dist-info/WHEEL
treys-0.1.7.dist-info/top_level.txt
treys-0.1.7.dist-info/RECORD
