Metadata-Version: 2.1
Name: treys
Version: 0.1.7
Summary: treys is a pure Python poker hand evaluation library
Home-page: https://github.com/ihendley/treys
Author: Will Drevo, Mark Saindon, Imran Hendley
License: MIT
Classifier: Development Status :: 3 - Alpha
Classifier: Intended Audience :: Developers
Classifier: Intended Audience :: Education
Classifier: Intended Audience :: Science/Research
Classifier: License :: OSI Approved :: MIT License
Classifier: Programming Language :: Python :: 3
Classifier: Topic :: Games/Entertainment
License-File: LICENSE
